pexpectparser/__init__.py
pexpectparser/pexpectParser.py
pexpectparser-0.1.1.dist-info/LICENSE
pexpectparser-0.1.1.dist-info/METADATA
pexpectparser-0.1.1.dist-info/WHEEL
pexpectparser-0.1.1.dist-info/top_level.txt
pexpectparser-0.1.1.dist-info/RECORD
