Metadata-Version: 2.1
Name: pexpectparser
Version: 0.1.1
Summary: A command line bot library using the pexpect library
Home-page: https://github.com/lorkaan/pexpectparser.git
Author: Laurkan Rodriguez
Author-email: laurkan@engineer.com
License: UNKNOWN
Download-URL: https://github.com/lorkaan/pexpectparser/archive/v0.1.1.tar.gz
Platform: UNKNOWN
Classifier: Intended Audience :: Developers
Classifier: Programming Language :: Python :: 3.8
Classifier: Operating System :: OS Independent
Requires-Dist: pexpect
Requires-Dist: parsegrammar
